crochet/__init__.py
crochet/__init__.pyi
crochet/_eventloop.py
crochet/_resultstore.py
crochet/_shutdown.py
crochet/_util.py
crochet/_version.py
crochet/mypy.py
crochet/py.typed
crochet/tests/__init__.py
crochet/tests/test_api.py
crochet/tests/test_logging.py
crochet/tests/test_mypy.py
crochet/tests/test_process.py
crochet/tests/test_resultstore.py
crochet/tests/test_setup.py
crochet/tests/test_shutdown.py
crochet/tests/test_util.py
crochet-2.1.1.dist-info/LICENSE
crochet-2.1.1.dist-info/METADATA
crochet-2.1.1.dist-info/WHEEL
crochet-2.1.1.dist-info/top_level.txt
crochet-2.1.1.dist-info/RECORD
