Metadata-Version: 2.1
Name: crochet
Version: 2.1.1
Summary: Use Twisted anywhere!
Home-page: https://github.com/itamarst/crochet
Maintainer: Itamar Turner-Trauring
Maintainer-email: itamar@itamarst.org
License: MIT
Keywords: twisted threading
Classifier: Intended Audience :: Developers
Classifier: License :: OSI Approved :: MIT License
Classifier: Operating System :: OS Independent
Classifier: Programming Language :: Python
Classifier: Programming Language :: Python :: 3.8
Classifier: Programming Language :: Python :: 3.9
Classifier: Programming Language :: Python :: 3.10
Classifier: Programming Language :: Python :: 3.11
Classifier: Programming Language :: Python :: Implementation :: CPython
Classifier: Programming Language :: Python :: Implementation :: PyPy
Requires-Python: >=3.8.0
License-File: LICENSE
